mlcolvar/__init__.py
mlcolvar/_version.py
mlcolvar/py.typed
mlcolvar/core/__init__.py
mlcolvar/core/loss/__init__.py
mlcolvar/core/loss/autocorrelation.py
mlcolvar/core/loss/committor_loss.py
mlcolvar/core/loss/eigvals.py
mlcolvar/core/loss/elbo.py
mlcolvar/core/loss/fisher.py
mlcolvar/core/loss/generator_loss.py
mlcolvar/core/loss/mse.py
mlcolvar/core/loss/tda_loss.py
mlcolvar/core/loss/utils/__init__.py
mlcolvar/core/loss/utils/smart_derivatives.py
mlcolvar/core/nn/__init__.py
mlcolvar/core/nn/feedforward.py
mlcolvar/core/nn/utils.py
mlcolvar/core/stats/__init__.py
mlcolvar/core/stats/lda.py
mlcolvar/core/stats/pca.py
mlcolvar/core/stats/stats.py
mlcolvar/core/stats/tica.py
mlcolvar/core/stats/utils.py
mlcolvar/core/transform/__init__.py
mlcolvar/core/transform/transform.py
mlcolvar/core/transform/utils.py
mlcolvar/core/transform/descriptors/__init__.py
mlcolvar/core/transform/descriptors/coordination_numbers.py
mlcolvar/core/transform/descriptors/eigs_adjacency_matrix.py
mlcolvar/core/transform/descriptors/multiple_descriptors.py
mlcolvar/core/transform/descriptors/pairwise_distances.py
mlcolvar/core/transform/descriptors/torsional_angle.py
mlcolvar/core/transform/descriptors/utils.py
mlcolvar/core/transform/tools/__init__.py
mlcolvar/core/transform/tools/continuous_hist.py
mlcolvar/core/transform/tools/normalization.py
mlcolvar/core/transform/tools/switching_functions.py
mlcolvar/core/transform/tools/utils.py
mlcolvar/cvs/__init__.py
mlcolvar/cvs/cv.py
mlcolvar/cvs/committor/__init__.py
mlcolvar/cvs/committor/committor.py
mlcolvar/cvs/committor/utils.py
mlcolvar/cvs/generator/__init__.py
mlcolvar/cvs/generator/generator.py
mlcolvar/cvs/generator/utils.py
mlcolvar/cvs/multitask/__init__.py
mlcolvar/cvs/multitask/multitask.py
mlcolvar/cvs/supervised/__init__.py
mlcolvar/cvs/supervised/deeplda.py
mlcolvar/cvs/supervised/deeptda.py
mlcolvar/cvs/supervised/regression.py
mlcolvar/cvs/timelagged/__init__.py
mlcolvar/cvs/timelagged/deeptica.py
mlcolvar-1.3.0.dist-info/licenses/LICENSE
mlcolvar-1.3.0.dist-info/METADATA
mlcolvar-1.3.0.dist-info/WHEEL
mlcolvar-1.3.0.dist-info/top_level.txt
mlcolvar-1.3.0.dist-info/RECORD
