Metadata-Version: 2.4
Name: mlcolvar
Version: 1.3.0
Summary: Machine learning collective variables for enhanced sampling
Author: Enrico Trizio, Andrea Rizzi, Michele Parrinello
Author-email: Luigi Bonati <luigi.bonati@iit.it>
License: MIT
Project-URL: Source, https://github.com/luigibonati/mlcolvar/
Project-URL: Documentation, https://mlcolvar.readthedocs.io/
Classifier: License :: OSI Approved :: MIT License
Classifier: Programming Language :: Python :: 3
Classifier: Development Status :: 3 - Alpha
Classifier: Intended Audience :: Science/Research
Classifier: Topic :: Scientific/Engineering
Classifier: Natural Language :: English
Requires-Python: >=3.8
License-File: LICENSE
Requires-Dist: lightning
Requires-Dist: torch
Requires-Dist: numpy
Requires-Dist: pandas
Requires-Dist: matplotlib
Requires-Dist: scipy
Requires-Dist: KDEpy
Requires-Dist: scikit-learn<1.8
Requires-Dist: pydantic<2
Provides-Extra: test
Requires-Dist: pytest>=6.1.2; extra == "test"
Requires-Dist: pytest-runner; extra == "test"
Requires-Dist: pytest-cov; extra == "test"
Requires-Dist: codecov; extra == "test"
Requires-Dist: nbmake; extra == "test"
Provides-Extra: doc
Requires-Dist: sphinx; extra == "doc"
Requires-Dist: nbsphinx; extra == "doc"
Requires-Dist: furo; extra == "doc"
Requires-Dist: sphinx-copybutton; extra == "doc"
Dynamic: license-file
